setup.py
medindex_firefighters_compare_pdf/__init__.py
medindex_firefighters_compare_pdf/pdf_image_compare.py
medindex_firefighters_compare_pdf/pdf_utils.py
medindex_firefighters_compare_pdf/utilities.py
medindex_firefighters_compare_pdf.egg-info/PKG-INFO
medindex_firefighters_compare_pdf.egg-info/SOURCES.txt
medindex_firefighters_compare_pdf.egg-info/dependency_links.txt
medindex_firefighters_compare_pdf.egg-info/top_level.txt