Metadata-Version: 1.2
Name: medindex-firefighters-compare-pdf
Version: 1.56
Summary: A package for internal usage in The Medindex ru for pdf image compare
Home-page: UNKNOWN
Author: kurzeneva.o
Author-email: kurzeneva.o@medindex.ru
License: UNKNOWN
Platform: UNKNOWN
Requires-Python: >=3.7
